cpp_init/__init__.py
cpp_init/__main__.py
cpp_init/cpp-init-res/CMakeLists.txt
cpp_init/cpp-init-res/CMakeMakefile
cpp_init/cpp-init-res/Makefile
cpp_init/cpp-init-res/_gitignore
cpp_init/cpp-init-res/lib.c
cpp_init/cpp-init-res/lib.cpp
cpp_init/cpp-init-res/lib.h
cpp_init/cpp-init-res/lib.hpp
cpp_init/cpp-init-res/main.c
cpp_init/cpp-init-res/main.cpp
cpp_init/cpp-init-res/main.h
cpp_init/cpp-init-res/main.hpp
cpp_init-1.3.0.dist-info/LICENSE
cpp_init-1.3.0.dist-info/METADATA
cpp_init-1.3.0.dist-info/WHEEL
cpp_init-1.3.0.dist-info/entry_points.txt
cpp_init-1.3.0.dist-info/top_level.txt
cpp_init-1.3.0.dist-info/RECORD
