Metadata-Version: 2.1
Name: cpp-init
Version: 1.3.0
Summary: A simple tool for setting up c/c++ projects.
Home-page: https://github.com/beProsto/cpp-init
Author: beProsto
Author-email: be1prosto@gmail.com
Classifier: Programming Language :: Python :: 3
Classifier: License :: OSI Approved :: MIT License
Classifier: Operating System :: OS Independent
Requires-Python: >=3.0
License-File: LICENSE
